{"Jonathan Taylor":{"mtfPerAtt":0.084,"brkTkl":27,"att":323,"successPct":44.4},"Christian McCaffrey":{"mtfPerAtt":0.032,"brkTkl":10,"att":311,"successPct":39.2},"James Cook":{"mtfPerAtt":0.068,"brkTkl":21,"att":309,"successPct":45.6},"Derrick Henry":{"mtfPerAtt":0.042,"brkTkl":13,"att":307,"successPct":41.7},"Bijan Robinson":{"mtfPerAtt":0.077,"brkTkl":22,"att":287,"successPct":41.3},"Saquon Barkley":{"mtfPerAtt":0.064,"brkTkl":18,"att":280,"successPct":37.7},"Ashton Jeanty":{"mtfPerAtt":0.09,"brkTkl":24,"att":266,"successPct":31.8},"Travis Etienne":{"mtfPerAtt":0.038,"brkTkl":10,"att":260,"successPct":35.8},"Kyren Williams":{"mtfPerAtt":0.085,"brkTkl":22,"att":259,"successPct":50.2},"Javonte Williams":{"mtfPerAtt":0.099,"brkTkl":25,"att":252,"successPct":45.6},"Jahmyr Gibbs":{"mtfPerAtt":0.074,"brkTkl":18,"att":243,"successPct":39.9},"Breece Hall":{"mtfPerAtt":0.049,"brkTkl":12,"att":243,"successPct":40.7},"Tony Pollard":{"mtfPerAtt":0.066,"brkTkl":16,"att":242,"successPct":39.3},"DeVon Achane":{"mtfPerAtt":0.092,"brkTkl":22,"att":238},"Rico Dowdle":{"mtfPerAtt":0.059,"brkTkl":14,"att":236,"successPct":42.2},"Josh Jacobs":{"mtfPerAtt":0.068,"brkTkl":16,"att":234,"successPct":43.6},"Chase Brown":{"mtfPerAtt":0.069,"brkTkl":16,"att":232,"successPct":39.9},"Quinshon Judkins":{"mtfPerAtt":0.048,"brkTkl":11,"att":230,"successPct":33.3},"DAndre Swift":{"mtfPerAtt":0.049,"brkTkl":11,"att":223},"Kenneth Walker":{"mtfPerAtt":0.104,"brkTkl":23,"att":221},"Jaylen Warren":{"mtfPerAtt":0.109,"brkTkl":23,"att":211,"successPct":42.7},"Woody Marks":{"mtfPerAtt":0.031,"brkTkl":6,"att":196,"successPct":36.2},"Zach Charbonnet":{"mtfPerAtt":0.076,"brkTkl":14,"att":184,"successPct":41.6},"TreVeyon Henderson":{"mtfPerAtt":0.061,"brkTkl":11,"att":180,"successPct":41.7},"Tyrone Tracy":{"mtfPerAtt":0.028,"brkTkl":5,"att":176},"Jacory Croskey-Merritt":{"mtfPerAtt":0.074,"brkTkl":13,"att":175,"successPct":42.6},"Bucky Irving":{"mtfPerAtt":0.058,"brkTkl":10,"att":173,"successPct":34.7},"Kyle Monangai":{"mtfPerAtt":0.03,"brkTkl":5,"att":169,"successPct":46.2},"Kareem Hunt":{"mtfPerAtt":0.043,"brkTkl":7,"att":163,"successPct":47.9},"Jordan Mason":{"mtfPerAtt":0.082,"brkTkl":13,"att":159,"successPct":46.5},"David Montgomery":{"mtfPerAtt":0.019,"brkTkl":3,"att":158,"successPct":43.4},"Kimani Vidal":{"mtfPerAtt":0.019,"brkTkl":3,"att":155,"successPct":36.1},"JK Dobbins":{"mtfPerAtt":0.059,"brkTkl":9,"att":153},"RJ Harvey":{"mtfPerAtt":0.048,"brkTkl":7,"att":146,"successPct":36.1},"Blake Corum":{"mtfPerAtt":0.083,"brkTkl":12,"att":145,"successPct":51},"Tyler Allgeier":{"mtfPerAtt":0.063,"brkTkl":9,"att":143,"successPct":39.9},"Chuba Hubbard":{"mtfPerAtt":0.007,"brkTkl":1,"att":134,"successPct":40.7},"Aaron Jones":{"mtfPerAtt":0.038,"brkTkl":5,"att":132,"successPct":43.2},"Rachaad White":{"mtfPerAtt":0.068,"brkTkl":9,"att":132,"successPct":48.1},"Alvin Kamara":{"mtfPerAtt":0.053,"brkTkl":7,"att":131,"successPct":32.1},"Rhamondre Stevenson":{"mtfPerAtt":0.123,"brkTkl":16,"att":130,"successPct":37.4},"Emanuel Wilson":{"mtfPerAtt":0.056,"brkTkl":7,"att":125,"successPct":44},"Omarion Hampton":{"mtfPerAtt":0.121,"brkTkl":15,"att":124,"successPct":41.9},"Nick Chubb":{"mtfPerAtt":0.041,"brkTkl":5,"att":122,"successPct":34.4},"Devin Singletary":{"mtfPerAtt":0.034,"brkTkl":4,"att":119,"successPct":38.7},"Isiah Pacheco":{"mtfPerAtt":0.017,"brkTkl":2,"att":118,"successPct":34.7},"Kenneth Gainwell":{"mtfPerAtt":0.123,"brkTkl":14,"att":114,"successPct":45.6},"Josh Allen":{"mtfPerAtt":0.063,"brkTkl":7,"att":112,"successPct":57.1},"Chris Rodriguez":{"mtfPerAtt":0.116,"brkTkl":13,"att":112},"Jalen Hurts":{"mtfPerAtt":0.029,"brkTkl":3,"att":105,"successPct":49.5},"Drake Maye":{"mtfPerAtt":0.019,"brkTkl":2,"att":103,"successPct":46.2},"Cam Skattebo":{"mtfPerAtt":0.069,"brkTkl":7,"att":101,"successPct":41.2},"Michael Carter":{"mtfPerAtt":0.033,"brkTkl":3,"att":92,"successPct":42.4},"Brian Robinson":{"mtfPerAtt":0.109,"brkTkl":10,"att":92,"successPct":43.5},"Jaxson Dart":{"mtfPerAtt":0,"brkTkl":0,"att":86,"successPct":61.6},"Sean Tucker":{"mtfPerAtt":0.058,"brkTkl":5,"att":86,"successPct":37.2},"Samaje Perine":{"mtfPerAtt":0.048,"brkTkl":4,"att":84,"successPct":54.8},"Justin Herbert":{"mtfPerAtt":0.036,"brkTkl":3,"att":83,"successPct":58.3},"Bo Nix":{"mtfPerAtt":0,"brkTkl":0,"att":83,"successPct":43.4},"Bhayshul Tuten":{"mtfPerAtt":0.06,"brkTkl":5,"att":83,"successPct":46.4},"Zonovan Knight":{"mtfPerAtt":0.061,"brkTkl":5,"att":82},"Trevor Lawrence":{"mtfPerAtt":0.061,"brkTkl":5,"att":82,"successPct":57.8},"Caleb Williams":{"mtfPerAtt":0.065,"brkTkl":5,"att":77,"successPct":48.1},"Tyjae Spears":{"mtfPerAtt":0.056,"brkTkl":4,"att":72,"successPct":34.7},"Justin Fields":{"mtfPerAtt":0.042,"brkTkl":3,"att":71,"successPct":58.9},"Ollie Gordon":{"mtfPerAtt":0.086,"brkTkl":6,"att":70},"Jaylen Wright":{"mtfPerAtt":0.086,"brkTkl":6,"att":70,"successPct":47.1},"Lamar Jackson":{"mtfPerAtt":0.104,"brkTkl":7,"att":67,"successPct":49.3},"Dylan Sampson":{"mtfPerAtt":0.092,"brkTkl":6,"att":65,"successPct":26.2},"Patrick Mahomes":{"mtfPerAtt":0.063,"brkTkl":4,"att":64,"successPct":60.9},"Tank Bigsby":{"mtfPerAtt":0.172,"brkTkl":10,"att":58,"successPct":47.6},"Keaton Mitchell":{"mtfPerAtt":0.034,"brkTkl":2,"att":59,"successPct":35.6},"Jayden Daniels":{"mtfPerAtt":0.069,"brkTkl":4,"att":58,"successPct":47.5},"Ray Davis":{"mtfPerAtt":0.052,"brkTkl":3,"att":58,"successPct":41.4},"Devin Neal":{"mtfPerAtt":0.018,"brkTkl":1,"att":57,"successPct":35.1},"Baker Mayfield":{"mtfPerAtt":0.127,"brkTkl":7,"att":55,"successPct":58.2},"Bryce Young":{"mtfPerAtt":0.037,"brkTkl":2,"att":54,"successPct":40.7},"Dak Prescott":{"mtfPerAtt":0.057,"brkTkl":3,"att":53,"successPct":41.5},"Malik Davis":{"mtfPerAtt":0,"brkTkl":0,"att":52,"successPct":40.4},"Taysom Hill":{"mtfPerAtt":0.038,"brkTkl":2,"att":52,"successPct":36.5},"Ty Johnson":{"mtfPerAtt":0.04,"brkTkl":2,"att":50,"successPct":50},"Marcus Mariota":{"mtfPerAtt":0,"brkTkl":0,"att":50,"successPct":46},"De'Von Achane":{"successPct":38.2},"Ollie Gordon II":{"successPct":40},"D'Andre Swift":{"successPct":48},"Tyrone Tracy Jr.":{"successPct":36.9},"Kenneth Walker III":{"successPct":38},"J.K. Dobbins":{"successPct":45.8},"Chris Rodriguez Jr.":{"successPct":46.4},"Bam Knight":{"successPct":37.3}}